[
  {
    "id": 1,
    "question": "안전 관련 명령어 중에서 'WAIT'의 기능은 무엇인가요?",
    "choices": [
      "A. 신호를 출력한다",
      "B. 특정 시간 동안 대기한다",
      "C. 로봇의 위치를 저장한다",
      "D. 모션을 정지한다"
    ],
    "answerIndex": 1
  },
  {
    "id": 2,
    "question": "'GOTO' 명령어의 주된 목적은 무엇인가요?",
    "choices": [
      "A. 특정 레이블로 이동한다",
      "B. 입력값을 출력한다",
      "C. 루프를 종료한다",
      "D. 변수를 초기화한다"
    ],
    "answerIndex": 0
  },
  {
    "id": 3,
    "question": "다음 중 로봇 언어에서 'IF' 명령어와 함께 사용될 수 있는 것은?",
    "choices": [
      "A. FOR",
      "B. GOSUB",
      "C. ELSEIF",
      "D. RETURN"
    ],
    "answerIndex": 2
  },
  {
    "id": 4,
    "question": "'MOVE' 명령어는 무엇을 수행하나요?",
    "choices": [
      "A. 로봇의 모션을 정의한다",
      "B. 로봇의 위치를 변경한다",
      "C. 신호를 출력한다",
      "D. 로봇의 상태를 확인한다"
    ],
    "answerIndex": 1
  },
  {
    "id": 5,
    "question": "'COLDET' 명령어는 어떤 기능을 수행하나요?",
    "choices": [
      "A. 충돌 감지를 수행한다",
      "B. 로봇의 경로를 지속적으로 계산한다",
      "C. 로봇의 속도를 조절한다",
      "D. 프로그램을 종료한다"
    ],
    "answerIndex": 0
  }
]